CHANGELOG.md
neptune_optuna/__init__.py
neptune_optuna/impl/__init__.py
neptune_optuna/impl/version.py
neptune_optuna-1.4.1.dist-info/LICENSE
neptune_optuna-1.4.1.dist-info/METADATA
neptune_optuna-1.4.1.dist-info/WHEEL
neptune_optuna-1.4.1.dist-info/RECORD
