Metadata-Version: 2.1
Name: neptune-optuna
Version: 1.4.1
Summary: Neptune.ai Optuna integration library
Home-page: https://neptune.ai/
License: Apache-2.0
Keywords: MLOps,ML Experiment Tracking,ML Model Registry,ML Model Store,ML Metadata Store
Author: neptune.ai
Author-email: contact@neptune.ai
Requires-Python: >=3.7,<4.0
Classifier: Development Status :: 5 - Production/Stable
Classifier: Environment :: Console
Classifier: Intended Audience :: Developers
Classifier: Intended Audience :: Science/Research
Classifier: License :: OSI Approved :: Apache Software License
Classifier: Natural Language :: English
Classifier: Operating System :: MacOS
Classifier: Operating System :: Microsoft :: Windows
Classifier: Operating System :: POSIX
Classifier: Operating System :: Unix
Classifier: Programming Language :: Python :: 3
Classifier: Programming Language :: Python :: 3.7
Classifier: Programming Language :: Python :: 3.8
Classifier: Programming Language :: Python :: 3.9
Classifier: Programming Language :: Python :: 3.10
Classifier: Programming Language :: Python :: 3.11
Classifier: Programming Language :: Python :: 3.12
Classifier: Programming Language :: Python :: 3.13
Classifier: Programming Language :: Python :: Implementation :: CPython
Classifier: Topic :: Scientific/Engineering :: Artificial Intelligence
Classifier: Topic :: Software Development :: Libraries :: Python Modules
Provides-Extra: dev
Requires-Dist: cffi ; extra == "dev"
Requires-Dist: deepdiff (==6.2.3) ; extra == "dev"
Requires-Dist: importlib-metadata ; python_version < "3.8"
Requires-Dist: neptune (>=1.0.0) ; extra == "dev"
Requires-Dist: numpy (<2.0) ; extra == "dev"
Requires-Dist: optuna (>=2.4.0)
Requires-Dist: plotly
Requires-Dist: pre-commit ; extra == "dev"
Requires-Dist: pytest (>=5.0) ; extra == "dev"
Requires-Dist: pytest-cov (==2.10.1) ; extra == "dev"
Requires-Dist: scikit-learn
Project-URL: Documentation, https://docs.neptune.ai/integrations/optuna/
Project-URL: Repository, https://github.com/neptune-ai/neptune-optuna
Project-URL: Tracker, https://github.com/neptune-ai/neptune-optuna/issues
